[
  {
    "id": "450b764b-995e-4f39-abd4-4882ef43102e",
    "data": [
      {
        "text": "half ",
        "userDefined": false
      },
      {
        "text": "meat",
        "alias": "toppings",
        "meta": "@toppings",
        "userDefined": false
      },
      {
        "text": " half ",
        "userDefined": false
      },
      {
        "text": "onions",
        "alias": "toppings1",
        "meta": "@toppings",
        "userDefined": false
      }
    ],
    "isTemplate": false,
    "count": 0,
    "updated": 1537837332
  },
  {
    "id": "6afedac6-6370-4796-b527-561000876407",
    "data": [
      {
        "text": "give me half with ",
        "userDefined": false
      },
      {
        "text": "mushrooms",
        "alias": "toppings",
        "meta": "@toppings",
        "userDefined": false
      },
      {
        "text": " and half with ",
        "userDefined": false
      },
      {
        "text": "onions",
        "alias": "toppings1",
        "meta": "@toppings",
        "userDefined": false
      }
    ],
    "isTemplate": false,
    "count": 0,
    "updated": 1537837332
  },
  {
    "id": "85071e51-9537-458e-8330-39e5cad5d552",
    "data": [
      {
        "text": "i want one with ",
        "userDefined": false
      },
      {
        "text": "mushrooms",
        "alias": "toppings",
        "meta": "@toppings",
        "userDefined": false
      },
      {
        "text": " and ",
        "userDefined": false
      },
      {
        "text": "one",
        "meta": "@sys.ignore",
        "userDefined": false
      },
      {
        "text": " with ",
        "userDefined": false
      },
      {
        "text": "sausages",
        "alias": "toppings1",
        "meta": "@toppings",
        "userDefined": false
      }
    ],
    "isTemplate": false,
    "count": 0,
    "updated": 1537837332
  }
]